frasco_images.py
setup.py
frasco_images.egg-info/PKG-INFO
frasco_images.egg-info/SOURCES.txt
frasco_images.egg-info/dependency_links.txt
frasco_images.egg-info/not-zip-safe
frasco_images.egg-info/requires.txt
frasco_images.egg-info/top_level.txt