Metadata-Version: 1.0
Name: frasco-images
Version: 0.1
Summary: Image manipulation for Frasco
Home-page: http://github.com/frascoweb/frasco-images
Author: Maxime Bouroumeau-Fuseau
Author-email: maxime.bouroumeau@gmail.com
License: MIT
Platform: any
